streaming_jupyter_integrations/__init__.py
streaming_jupyter_integrations/cast_utils.py
streaming_jupyter_integrations/config_utils.py
streaming_jupyter_integrations/deployment_bar.py
streaming_jupyter_integrations/display.py
streaming_jupyter_integrations/jar_handler.py
streaming_jupyter_integrations/magics.py
streaming_jupyter_integrations/reflection.py
streaming_jupyter_integrations/schema_view.py
streaming_jupyter_integrations/sql_syntax_highlighting.py
streaming_jupyter_integrations/sql_utils.py
streaming_jupyter_integrations/variable_substitution.py
streaming_jupyter_integrations/yarn.py
streaming_jupyter_integrations/labextension/package.json
streaming_jupyter_integrations/labextension/static/475.c11e6a9140b0560e4970.js
streaming_jupyter_integrations/labextension/static/remoteEntry.5fb1d162061fe8733975.js
streaming_jupyter_integrations/labextension/static/style.js
streaming_jupyter_integrations/labextension/static/third-party-licenses.json
streaming_jupyter_integrations-0.15.1.data/data/share/jupyter/labextensions/flink_sql_lsp_extension/install.json
streaming_jupyter_integrations-0.15.1.data/data/share/jupyter/labextensions/flink_sql_lsp_extension/package.json
streaming_jupyter_integrations-0.15.1.data/data/share/jupyter/labextensions/flink_sql_lsp_extension/static/475.c11e6a9140b0560e4970.js
streaming_jupyter_integrations-0.15.1.data/data/share/jupyter/labextensions/flink_sql_lsp_extension/static/remoteEntry.5fb1d162061fe8733975.js
streaming_jupyter_integrations-0.15.1.data/data/share/jupyter/labextensions/flink_sql_lsp_extension/static/style.js
streaming_jupyter_integrations-0.15.1.data/data/share/jupyter/labextensions/flink_sql_lsp_extension/static/third-party-licenses.json
streaming_jupyter_integrations-0.15.1.dist-info/LICENSE
streaming_jupyter_integrations-0.15.1.dist-info/METADATA
streaming_jupyter_integrations-0.15.1.dist-info/WHEEL
streaming_jupyter_integrations-0.15.1.dist-info/top_level.txt
streaming_jupyter_integrations-0.15.1.dist-info/RECORD
