Metadata-Version: 2.1
Name: streaming-jupyter-integrations
Version: 0.15.1
Summary: JupyterNotebook Flink magics
Home-page: https://github.com/getindata/streaming-jupyter-integrations
Author: GetInData
Author-email: office@getindata.com
License: Apache Software License (Apache 2.0)
Keywords: jupyter flink sql ipython
Classifier: Programming Language :: Python :: 3.7
Classifier: Programming Language :: Python :: 3.8
Classifier: Operating System :: OS Independent
Requires-Python: >=3.7
License-File: LICENSE
Requires-Dist: ipython <8.9,>=7.0
Requires-Dist: ipytree ~=0.2.0
Requires-Dist: wget ~=3.2.0
Requires-Dist: sqlparse ~=0.4.0
Requires-Dist: pyyaml ~=6.0.0
Requires-Dist: types-PyYAML ~=6.0.0
Requires-Dist: yarn-api-client ~=1.0.0
Requires-Dist: ipywidgets
Requires-Dist: apache-flink <=1.18,>=1.15
Requires-Dist: pandas
Requires-Dist: py4j
Requires-Dist: requests
Requires-Dist: jupyterlab-lsp
Provides-Extra: tests
Requires-Dist: pytest <7.0.0,>=6.2.2 ; extra == 'tests'
Requires-Dist: pytest-cov <3.0.0,>=2.8.0 ; extra == 'tests'
Requires-Dist: pre-commit ==2.15.0 ; extra == 'tests'
Requires-Dist: tox ==3.21.1 ; extra == 'tests'
Requires-Dist: jupyter-packaging >=0.12.2 ; extra == 'tests'
Requires-Dist: responses >=0.22.0 ; extra == 'tests'
